{
  "project_info": {
    "project_number": "24075259655",
    "project_id": "day-counter-42ed2",
    "storage_bucket": "day-counter-42ed2.firebasestorage.app"
  },
  "client": [
    {
      "client_info": {
        "mobilesdk_app_id": "1:24075259655:android:e4eb9bb8068850a8223fa2",
        "android_client_info": {
          "package_name": "com.example.d"
        }
      },
      "oauth_client": [],
      "api_key": [
        {
          "current_key": "AIzaSyB-8y0M605pxjpgAjEhCEldTVRcluvfI0g"
        }
      ],
      "services": {
        "appinvite_service": {
          "other_platform_oauth_client": []
        }
      }
    }
  ],
  "configuration_version": "1"
}